{
    "name": "Skeleventy",
    "url": "https://skeleventy.netlify.com",
    "author": {
        "name": "Max Power",
        "email": "hello@maxpower.com",
        "handle": "@maxpower",
        "avatar": "/images/blog/author.jpg"
    },
    "images": {
        "favicon": "/images/favicon.ico",
        "twitter": "/images/meta/twitter.jpg",
        "og": "/images/meta/og.jpg"
    },
    "social_links": {
        "facebook": "https://www.facebook.com",
        "twitter": "https://twitter.com/joe_dyer1",
        "linkedin": "https://www.linkedin.com"
    }
}
